ario/__init__.py
ario/application.py
ario/content.py
ario/exceptions.py
ario/jinja.py
ario/request.py
ario/response.py
ario/router.py
ario/static.py
ario/status.py
ario/document/__init__.py
ario/document/api.py
ario/document/ario_doc.py
ario/document/templates/doc.html
ario/document/templates/static/style.css
ario-0.6.9.dist-info/LICENSE
ario-0.6.9.dist-info/METADATA
ario-0.6.9.dist-info/WHEEL
ario-0.6.9.dist-info/top_level.txt
ario-0.6.9.dist-info/RECORD
