Metadata-Version: 2.1
Name: ario
Version: 0.6.9
Summary: A PYTHON Micro-Framework For Web Development. API Documentation Is Now Available.
Home-page: https://github.com/wish-team/ario
Author: Wish Team
License: UNKNOWN
Platform: UNKNOWN
Requires-Dist: Jinja2 (==2.11.2)
Requires-Dist: ujson (==3.2.0)
Requires-Dist: Werkzeug (==1.0.1)
Requires-Dist: urllib3 (>=1.25.10)
